printnum/PrintNumAtoms.py
printnum/__init__.py
printnum-0.1.6.dist-info/LICENSE
printnum-0.1.6.dist-info/METADATA
printnum-0.1.6.dist-info/WHEEL
printnum-0.1.6.dist-info/top_level.txt
printnum-0.1.6.dist-info/RECORD
