Metadata-Version: 2.1
Name: printnum
Version: 0.1.6
Summary: Printing a number of atoms in a molecule
Home-page: https://github.com/alena-lark/PrintNumAtom
Author: alena-lark
Author-email: AllyLarck@yandex.com
License: UNKNOWN
Platform: UNKNOWN
Classifier: Programming Language :: Python :: 3
Classifier: License :: OSI Approved :: MIT License
Classifier: Operating System :: OS Independent
Requires-Python: >=3.7
Requires-Dist: numpy
